astroARIADNE/__init__.py
astroARIADNE/config.py
astroARIADNE/error.py
astroARIADNE/fitter.py
astroARIADNE/isochrone.py
astroARIADNE/librarian.py
astroARIADNE/phot_utils.py
astroARIADNE/plotter.py
astroARIADNE/sed_library.py
astroARIADNE/star.py
astroARIADNE/utils.py
astroARIADNE/Datafiles/Template_prior.dat
astroARIADNE/Datafiles/mamajek_spt.dat
astroARIADNE/Datafiles/model_grid_fix.dat
astroARIADNE/Datafiles/plot_settings.dat
astroARIADNE/Datafiles/model_grids/BTCond_DF.pkl
astroARIADNE/Datafiles/model_grids/BTNextGen_DF.pkl
astroARIADNE/Datafiles/model_grids/BTSettl_DF.pkl
astroARIADNE/Datafiles/model_grids/CK04_DF.pkl
astroARIADNE/Datafiles/model_grids/Coelho_DF.pkl
astroARIADNE/Datafiles/model_grids/Kurucz_DF.pkl
astroARIADNE/Datafiles/model_grids/Phoenixv2_DF.pkl
astroARIADNE/Datafiles/model_grids/model_grid_BT_Cond.dat
astroARIADNE/Datafiles/model_grids/model_grid_BT_NextGen.dat
astroARIADNE/Datafiles/model_grids/model_grid_BT_Settl.dat
astroARIADNE/Datafiles/model_grids/model_grid_CK04.dat
astroARIADNE/Datafiles/model_grids/model_grid_Coelho.dat
astroARIADNE/Datafiles/model_grids/model_grid_Kurucz.dat
astroARIADNE/Datafiles/model_grids/model_grid_Phoenixv2.dat
astroARIADNE/Datafiles/prior/logg_kde.pkl
astroARIADNE/Datafiles/prior/logg_ppf.pkl
astroARIADNE/Datafiles/prior/teff_kde.pkl
astroARIADNE/Datafiles/prior/teff_ppf.pkl
astroARIADNE/Datafiles/prior/z_logg_kde.pkl
astroariadne-1.3.1.dist-info/licenses/LICENSE
astroariadne-1.3.1.dist-info/METADATA
astroariadne-1.3.1.dist-info/WHEEL
astroariadne-1.3.1.dist-info/top_level.txt
astroariadne-1.3.1.dist-info/RECORD
