Metadata-Version: 2.4
Name: astroARIADNE
Version: 1.3.1
Summary: Bayesian Model Averaging SED fitter
Home-page: https://github.com/jvines/astroARIADNE
Author: Jose Vines
Author-email: Jose Vines <jose.vines@ug.uchile.cl>
Maintainer: Jose Vines
Maintainer-email: Jose Vines <jose.vines@ug.uchile.cl>
License: MIT
Project-URL: Homepage, https://github.com/jvines/astroARIADNE
Classifier: Development Status :: 5 - Production/Stable
Classifier: Intended Audience :: Science/Research
Classifier: Programming Language :: Python :: 3
Classifier: Programming Language :: Python :: 3.11
Classifier: Programming Language :: Python :: 3.12
Classifier: Operating System :: MacOS :: MacOS X
Classifier: Operating System :: Unix
Classifier: Topic :: Scientific/Engineering :: Astronomy
Requires-Python: >=3.11
License-File: LICENSE
Requires-Dist: numpy>=1.26.0
Requires-Dist: scipy>=1.15.0
Requires-Dist: pandas>=2.2.0
Requires-Dist: numba>=0.61.0
Requires-Dist: astropy>=7.0.0
Requires-Dist: astroquery>=0.4.9
Requires-Dist: regions>=0.10
Requires-Dist: PyAstronomy>=0.22.0
Requires-Dist: tqdm>=4.67.0
Requires-Dist: matplotlib>=3.10.0
Requires-Dist: termcolor>=2.5.0
Requires-Dist: extinction>=0.4.7
Requires-Dist: pyphot>=1.6.0
Requires-Dist: dustmaps>=1.0.13
Requires-Dist: dynesty>=2.1.0
Requires-Dist: corner>=2.2.3
Requires-Dist: h5py>=3.12.0
Requires-Dist: tabulate>=0.9.0
Requires-Dist: isochrones>=2.1
Dynamic: author
Dynamic: home-page
Dynamic: license-file
Dynamic: maintainer
Dynamic: requires-python
